[{"FM3":"FamixTypeScript.Class","id":4,"sourceAnchor":{"ref":5},"name":"Recipe","container":{"ref":3},"attributes":[{"ref":10},{"ref":17},{"ref":21},{"ref":27},{"ref":32}],"isInterface":false},{"FM3":"FamixTypeScript.CustomSourceLanguage","id":1,"name":"TypeScript"},{"FM3":"FamixTypeScript.IndexedFileAnchor","id":2,"fileName":"/home/vince/Repos/MGL843/nest/sample/23-graphql-code-first/src/recipes/models/recipe.model.ts","startPos":0,"endPos":327},{"FM3":"FamixTypeScript.Namespace","id":3,"name":"DefaultNamespace","types":[{"ref":4}]},{"FM3":"FamixTypeScript.IndexedFileAnchor","id":5,"element":{"ref":4},"fileName":"/home/vince/Repos/MGL843/nest/sample/23-graphql-code-first/src/recipes/models/recipe.model.ts","startPos":58,"endPos":326},{"FM3":"FamixTypeScript.Decorator","id":6,"sourceAnchor":{"ref":9},"name":"ObjectType","parameters":[{"ref":7}],"container":{"ref":3},"decoratorType":"Class","decoratedEntity":{"ref":4},"isFactory":true},{"FM3":"FamixTypeScript.Parameter","id":7,"sourceAnchor":{"ref":8},"name":"{ description: 'recipe ' }","parentBehaviouralEntity":{"ref":6}},{"FM3":"FamixTypeScript.IndexedFileAnchor","id":8,"element":{"ref":7},"fileName":"/home/vince/Repos/MGL843/nest/sample/23-graphql-code-first/src/recipes/models/recipe.model.ts","startPos":70,"endPos":96},{"FM3":"FamixTypeScript.IndexedFileAnchor","id":9,"element":{"ref":6},"fileName":"/home/vince/Repos/MGL843/nest/sample/23-graphql-code-first/src/recipes/models/recipe.model.ts","startPos":58,"endPos":97},{"FM3":"FamixTypeScript.Attribute","id":10,"sourceAnchor":{"ref":12},"name":"id","declaredType":{"ref":11},"hasClassScope":true,"parentType":{"ref":4}},{"FM3":"FamixTypeScript.Type","id":11,"name":"string","structuresWithDeclaredType":[{"ref":10},{"ref":17},{"ref":21}]},{"FM3":"FamixTypeScript.IndexedFileAnchor","id":12,"element":{"ref":10},"fileName":"/home/vince/Repos/MGL843/nest/sample/23-graphql-code-first/src/recipes/models/recipe.model.ts","startPos":122,"endPos":154},{"FM3":"FamixTypeScript.Decorator","id":13,"sourceAnchor":{"ref":16},"name":"Field","parameters":[{"ref":14}],"container":{"ref":3},"decoratorType":"Property","decoratedEntity":{"ref":10},"isFactory":true},{"FM3":"FamixTypeScript.Parameter","id":14,"sourceAnchor":{"ref":15},"name":"type => ID","parentBehaviouralEntity":{"ref":13}},{"FM3":"FamixTypeScript.IndexedFileAnchor","id":15,"element":{"ref":14},"fileName":"/home/vince/Repos/MGL843/nest/sample/23-graphql-code-first/src/recipes/models/recipe.model.ts","startPos":129,"endPos":139},{"FM3":"FamixTypeScript.IndexedFileAnchor","id":16,"element":{"ref":13},"fileName":"/home/vince/Repos/MGL843/nest/sample/23-graphql-code-first/src/recipes/models/recipe.model.ts","startPos":122,"endPos":140},{"FM3":"FamixTypeScript.Attribute","id":17,"sourceAnchor":{"ref":18},"name":"title","declaredType":{"ref":11},"hasClassScope":true,"parentType":{"ref":4}},{"FM3":"FamixTypeScript.IndexedFileAnchor","id":18,"element":{"ref":17},"fileName":"/home/vince/Repos/MGL843/nest/sample/23-graphql-code-first/src/recipes/models/recipe.model.ts","startPos":158,"endPos":183},{"FM3":"FamixTypeScript.Decorator","id":19,"sourceAnchor":{"ref":20},"name":"Field","container":{"ref":3},"decoratorType":"Property","decoratedEntity":{"ref":17},"isFactory":true},{"FM3":"FamixTypeScript.IndexedFileAnchor","id":20,"element":{"ref":19},"fileName":"/home/vince/Repos/MGL843/nest/sample/23-graphql-code-first/src/recipes/models/recipe.model.ts","startPos":158,"endPos":166},{"FM3":"FamixTypeScript.Attribute","id":21,"sourceAnchor":{"ref":22},"name":"description","declaredType":{"ref":11},"hasClassScope":true,"parentType":{"ref":4}},{"FM3":"FamixTypeScript.IndexedFileAnchor","id":22,"element":{"ref":21},"fileName":"/home/vince/Repos/MGL843/nest/sample/23-graphql-code-first/src/recipes/models/recipe.model.ts","startPos":187,"endPos":237},{"FM3":"FamixTypeScript.Decorator","id":23,"sourceAnchor":{"ref":26},"name":"Field","parameters":[{"ref":24}],"container":{"ref":3},"decoratorType":"Property","decoratedEntity":{"ref":21},"isFactory":true},{"FM3":"FamixTypeScript.Parameter","id":24,"sourceAnchor":{"ref":25},"name":"{ nullable: true }","parentBehaviouralEntity":{"ref":23}},{"FM3":"FamixTypeScript.IndexedFileAnchor","id":25,"element":{"ref":24},"fileName":"/home/vince/Repos/MGL843/nest/sample/23-graphql-code-first/src/recipes/models/recipe.model.ts","startPos":194,"endPos":212},{"FM3":"FamixTypeScript.IndexedFileAnchor","id":26,"element":{"ref":23},"fileName":"/home/vince/Repos/MGL843/nest/sample/23-graphql-code-first/src/recipes/models/recipe.model.ts","startPos":187,"endPos":213},{"FM3":"FamixTypeScript.Attribute","id":27,"sourceAnchor":{"ref":29},"name":"creationDate","declaredType":{"ref":28},"hasClassScope":true,"parentType":{"ref":4}},{"FM3":"FamixTypeScript.Type","id":28,"name":"Date","structuresWithDeclaredType":[{"ref":27}]},{"FM3":"FamixTypeScript.IndexedFileAnchor","id":29,"element":{"ref":27},"fileName":"/home/vince/Repos/MGL843/nest/sample/23-graphql-code-first/src/recipes/models/recipe.model.ts","startPos":241,"endPos":271},{"FM3":"FamixTypeScript.Decorator","id":30,"sourceAnchor":{"ref":31},"name":"Field","container":{"ref":3},"decoratorType":"Property","decoratedEntity":{"ref":27},"isFactory":true},{"FM3":"FamixTypeScript.IndexedFileAnchor","id":31,"element":{"ref":30},"fileName":"/home/vince/Repos/MGL843/nest/sample/23-graphql-code-first/src/recipes/models/recipe.model.ts","startPos":241,"endPos":249},{"FM3":"FamixTypeScript.Attribute","id":32,"sourceAnchor":{"ref":34},"name":"ingredients","declaredType":{"ref":33},"hasClassScope":true,"parentType":{"ref":4}},{"FM3":"FamixTypeScript.Type","id":33,"name":"string[]","structuresWithDeclaredType":[{"ref":32}]},{"FM3":"FamixTypeScript.IndexedFileAnchor","id":34,"element":{"ref":32},"fileName":"/home/vince/Repos/MGL843/nest/sample/23-graphql-code-first/src/recipes/models/recipe.model.ts","startPos":275,"endPos":324},{"FM3":"FamixTypeScript.Decorator","id":35,"sourceAnchor":{"ref":38},"name":"Field","parameters":[{"ref":36}],"container":{"ref":3},"decoratorType":"Property","decoratedEntity":{"ref":32},"isFactory":true},{"FM3":"FamixTypeScript.Parameter","id":36,"sourceAnchor":{"ref":37},"name":"type => [String]","parentBehaviouralEntity":{"ref":35}},{"FM3":"FamixTypeScript.IndexedFileAnchor","id":37,"element":{"ref":36},"fileName":"/home/vince/Repos/MGL843/nest/sample/23-graphql-code-first/src/recipes/models/recipe.model.ts","startPos":282,"endPos":298},{"FM3":"FamixTypeScript.IndexedFileAnchor","id":38,"element":{"ref":35},"fileName":"/home/vince/Repos/MGL843/nest/sample/23-graphql-code-first/src/recipes/models/recipe.model.ts","startPos":275,"endPos":299}]